oxidized_importer.cpython-310-x86_64-linux-gnu.so
oxidized_importer-0.6.0.dist-info/WHEEL
oxidized_importer-0.6.0.dist-info/top_level.txt
oxidized_importer-0.6.0.dist-info/LICENSE
oxidized_importer-0.6.0.dist-info/METADATA
oxidized_importer-0.6.0.dist-info/RECORD
