Metadata-Version: 2.1
Name: oxidized-importer
Version: 0.6.0
Summary: Python importer implemented in Rust
Home-page: https://github.com/indygreg/PyOxidizer
Author: Gregory Szorc
Author-email: gregory.szorc@gmail.com
License: MPL 2.0
Platform: UNKNOWN
Classifier: Intended Audience :: Developers
Classifier: Programming Language :: Rust
Requires-Python: >=3.8
License-File: LICENSE
